tamil_sentence_extractor/__init__.py
tamil_sentence_extractor/extractor.py
tamil_sentence_extractor-0.2.dist-info/METADATA
tamil_sentence_extractor-0.2.dist-info/WHEEL
tamil_sentence_extractor-0.2.dist-info/top_level.txt
tamil_sentence_extractor-0.2.dist-info/RECORD
