Metadata-Version: 2.1
Name: tamil_sentence_extractor
Version: 0.2
Summary: A simple Python module for extracting Tamil sentences from text.
Author: Sathishkumar K
Author-email: sathish30062002@gmail.com
Requires-Python: >=3.6
